{
	"entries": [
		{
				"message": "Running HolidaysByCountryViaAPI_v2.script",
				"identifier": "START",
				"timestamp": "2025-04-01 13:04:53.063 -0400"
			},
		{
				"handlerName": "on_holidaysbycountryviaapi_v2",
				"timestamp": "2025-04-01 13:04:53.102 -0400",
				"message": "The target date is 2024-12-26",
				"scriptName": "HolidaysByCountryViaAPI_v2.script",
				"handlerLine": 5,
				"identifier": "Log"
			},
		{
				"handlerName": "on_holidaysbycountryviaapi_v2",
				"timestamp": "2025-04-01 13:04:53.119 -0400",
				"message": "The queried country codes are [\"US\",\"DE\",\"GB\"]",
				"scriptName": "HolidaysByCountryViaAPI_v2.script",
				"handlerLine": 12,
				"identifier": "Log"
			},
		{
				"message": "(Duration:\"9.754\", Errors:\"1\", Exceptions:\"0\", StartTime:\"2025-04-01 13:04:53 -0400\", Successes:\"0\", TestCase:\"HolidaysByCountryViaAPI_v2.script\", Warnings:\"0\")",
				"identifier": "EndTestCase",
				"timestamp": "2025-04-01 13:05:02.819 -0400"
			},
		{
				"message": "Execution Time 0:00:09 HolidaysByCountryViaAPI_v2.script",
				"identifier": "ABORTED",
				"timestamp": "2025-04-01 13:05:02.830 -0400"
			}
	],
	"createdTimestamp": "2025-04-01 13:04:53.065 -0400"
}