{
	"entries": [
		{
				"message": "Running stockAPIDataDriven.script",
				"identifier": "START",
				"timestamp": "2024-07-11 11:58:24.155 -0400"
			},
		{
				"message": "(Duration:\"2013.871\", Errors:\"1\", Exceptions:\"0\", StartTime:\"2024-07-11 11:58:24 -0400\", Successes:\"0\", TestCase:\"stockAPIDataDriven.script\", Warnings:\"0\")",
				"identifier": "EndTestCase",
				"timestamp": "2024-07-11 12:31:58.043 -0400"
			},
		{
				"message": "Execution Time 0:33:33 stockAPIDataDriven.script",
				"identifier": "ABORTED",
				"timestamp": "2024-07-11 12:31:58.089 -0400"
			}
	],
	"createdTimestamp": "2024-07-11 11:58:24.166 -0400"
}